ocr_shell/__init__.py
ocr_shell/ocr.py
tests/__init__.py
tests/test_ocr.py
ocr_shell-0.2.0.dist-info/LICENSE
ocr_shell-0.2.0.dist-info/METADATA
ocr_shell-0.2.0.dist-info/WHEEL
ocr_shell-0.2.0.dist-info/entry_points.txt
ocr_shell-0.2.0.dist-info/top_level.txt
ocr_shell-0.2.0.dist-info/RECORD
