Metadata-Version: 2.1
Name: ocr-shell
Version: 0.2.0
Summary: A wrapper around tesseract that can be easily called from the command line on an image from the clipboard
Home-page: https://github.com/kyrrigle/ocr-shell
Author: Matthew King
Author-email: kyrrigle@gmail.com
License: MIT
License-File: LICENSE
Requires-Dist: docopt
Requires-Dist: Pillow
Requires-Dist: pytesseract
